video_resizer/__init__.py
video_resizer/cli.py
video_resizer/resizer.py
video_resizer-1.3.dist-info/METADATA
video_resizer-1.3.dist-info/WHEEL
video_resizer-1.3.dist-info/entry_points.txt
video_resizer-1.3.dist-info/top_level.txt
video_resizer-1.3.dist-info/RECORD
